HappySearch/__init__.py
HappySearch-0.0.1.dist-info/LICENSE
HappySearch-0.0.1.dist-info/METADATA
HappySearch-0.0.1.dist-info/WHEEL
HappySearch-0.0.1.dist-info/top_level.txt
HappySearch-0.0.1.dist-info/RECORD
